piskle/__init__.py
piskle/_piskle_initializer.py
piskle/partial_object.py
piskle/partializer.py
piskle/piskle.py
piskle/sklearn_piskle_partializer.py
piskle/utils.py
piskle-0.1.2.dist-info/LICENSE
piskle-0.1.2.dist-info/METADATA
piskle-0.1.2.dist-info/WHEEL
piskle-0.1.2.dist-info/top_level.txt
piskle-0.1.2.dist-info/RECORD
