Metadata-Version: 2.1
Name: piskle
Version: 0.1.2
Summary: Piskle allows you to selectively and efficiently serialize scikit-learn models to save on memory and load times.
Home-page: https://github.com/hmiladhia/piskle
Author: Amal HASNI, Dhia HMILA
Author-email: emerald.snippets@gmail.com
License: MIT
Keywords: serialization,scikit-learn,export,pickle,models,objects,joblib,estimators
Platform: UNKNOWN
Classifier: Development Status :: 4 - Beta
Classifier: Programming Language :: Python :: 3
Classifier: License :: OSI Approved :: MIT License
Classifier: Operating System :: OS Independent
Requires-Python: >=3.6
Requires-Dist: scikit-learn (==0.24.0)
